edfig/__init__.py
edfig-0.0.1.dist-info/METADATA
edfig-0.0.1.dist-info/WHEEL
edfig-0.0.1.dist-info/top_level.txt
edfig-0.0.1.dist-info/RECORD
